Workbook

Sheet Simulador
A1: SIMULADOR DE INVESTIMENTOS FII
A4: Salário | B4: 5000 | D4: Patrimônio Acumulado | E4: =VF(B7,B6*12,-B5,0,0) | G4: Tipo Fundo | H4: %
A5: Aporte Mensal | B5: 1500 | D5: Dividendos Mensais | E5: =E4*B7 | G5: Papel | H5: =PROCV($B$8&G5,Apoio!$D$2:$E$19,2,FALSO)
A6: Prazo (anos) | B6: 10 | G6: Tijolo | H6: =PROCV($B$8&G6,Apoio!$D$2:$E$19,2,FALSO)
A7: Taxa Mensal | B7: 0.01 | G7: Hibrido | H7: =PROCV($B$8&G7,Apoio!$D$2:$E$19,2,FALSO)
A8: Perfil | B8: Moderado | D8: Cenários | G8: FOF | H8: =PROCV($B$8&G8,Apoio!$D$2:$E$19,2,FALSO)
D9: Anos | E9: Patrimônio | G9: Hotel | H9: =PROCV($B$8&G9,Apoio!$D$2:$E$19,2,FALSO)
D10: 2 | E10: =VF($B$7,D10*12,-$B$5,0,0) | G10: Desenv | H10: =PROCV($B$8&G10,Apoio!$D$2:$E$19,2,FALSO)
D11: 5 | E11: =VF($B$7,D11*12,-$B$5,0,0)
D12: 10 | E12: =VF($B$7,D12*12,-$B$5,0,0)
D13: 20 | E13: =VF($B$7,D13*12,-$B$5,0,0)
D14: 30 | E14: =VF($B$7,D14*12,-$B$5,0,0)

Sheet Apoio
A1: Perfil | B1: Fundo | C1: Percentual | D1: Chave
A2: Conservador | B2: Papel | C2: 40 | D2: ConservadorPapel | E2: =C2/100
A3: Conservador | B3: Tijolo | C3: 25 | D3: ConservadorTijolo | E3: =C3/100
A4: Conservador | B4: Hibrido | C4: 15 | D4: ConservadorHibrido | E4: =C4/100
A5: Conservador | B5: FOF | C5: 10 | D5: ConservadorFOF | E5: =C5/100
A6: Conservador | B6: Hotel | C6: 5 | D6: ConservadorHotel | E6: =C6/100
A7: Conservador | B7: Desenv | C7: 5 | D7: ConservadorDesenv | E7: =C7/100
A8: Moderado | B8: Papel | C8: 30 | D8: ModeradoPapel | E8: =C8/100
A9: Moderado | B9: Tijolo | C9: 25 | D9: ModeradoTijolo | E9: =C9/100
A10: Moderado | B10: Hibrido | C10: 20 | D10: ModeradoHibrido | E10: =C10/100
A11: Moderado | B11: FOF | C11: 10 | D11: ModeradoFOF | E11: =C11/100
A12: Moderado | B12: Hotel | C12: 5 | D12: ModeradoHotel | E12: =C12/100
A13: Moderado | B13: Desenv | C13: 10 | D13: ModeradoDesenv | E13: =C13/100
... A19: Agressivo | B19: Desenv | C19: 20 | D19: AgressivoDesenv | E19: =C19/100
